<?xml version="1.0" encoding="UTF-8"?>
<!DOCTYPE mapper PUBLIC "-//mybatis.org//DTD Mapper 3.0//EN" "http://mybatis.org/dtd/mybatis-3-mapper.dtd">
<mapper namespace="com.fashion.mjysite.mapper.ArticleMapper">
  <resultMap id="BaseResultMap" type="com.fashion.mjysite.entity.Article">
    <!--
      WARNING - @mbg.generated
      This element is automatically generated by MyBatis Generator, do not modify.
      This element was generated on Wed Aug 29 11:55:59 CST 2018.
    -->
    <id column="id" jdbcType="BIGINT" property="id" />
    <result column="articleid" jdbcType="BIGINT" property="articleid" />
    <result column="article" jdbcType="LONGVARCHAR" property="article" />
  </resultMap>
  <delete id="deleteByPrimaryKey" parameterType="java.lang.Long">
    <!--
      WARNING - @mbg.generated
      This element is automatically generated by MyBatis Generator, do not modify.
      This element was generated on Wed Aug 29 11:55:59 CST 2018.
    -->
    delete from sys_article
    where id = #{id,jdbcType=BIGINT}
  </delete>
  <insert id="insert" parameterType="com.fashion.mjysite.entity.Article">
    <!--
      WARNING - @mbg.generated
      This element is automatically generated by MyBatis Generator, do not modify.
      This element was generated on Wed Aug 29 11:55:59 CST 2018.
    -->
    insert into sys_article (id, articleid, article
      )
    values (#{id,jdbcType=BIGINT}, #{articleid,jdbcType=BIGINT}, #{article,jdbcType=LONGVARCHAR}
      )
  </insert>
  <update id="updateByPrimaryKey" parameterType="com.fashion.mjysite.entity.Article">
    <!--
      WARNING - @mbg.generated
      This element is automatically generated by MyBatis Generator, do not modify.
      This element was generated on Wed Aug 29 11:55:59 CST 2018.
    -->
    update sys_article
    set articleid = #{articleid,jdbcType=BIGINT},
      article = #{article,jdbcType=LONGVARCHAR}
    where id = #{id,jdbcType=BIGINT}
  </update>
  <select id="selectByPrimaryKey" parameterType="java.lang.Long" resultMap="BaseResultMap">
    <!--
      WARNING - @mbg.generated
      This element is automatically generated by MyBatis Generator, do not modify.
      This element was generated on Wed Aug 29 11:55:59 CST 2018.
    -->
    select id, articleid, article
    from sys_article
    where id = #{id,jdbcType=BIGINT}
  </select>
  <select id="selectAll" resultMap="BaseResultMap">
    <!--
      WARNING - @mbg.generated
      This element is automatically generated by MyBatis Generator, do not modify.
      This element was generated on Wed Aug 29 11:55:59 CST 2018.
    -->
    select id, articleid, article
    from sys_article
  </select>
</mapper>